MANIFEST.in
README.rst
setup.py
bin/format-imports.py
importformatter/__init__.py
importformatter/stdlib.txt
importformatter.egg-info/PKG-INFO
importformatter.egg-info/SOURCES.txt
importformatter.egg-info/dependency_links.txt
importformatter.egg-info/not-zip-safe
importformatter.egg-info/top_level.txt