Metadata-Version: 1.0
Name: importformatter
Version: 0.1.3
Summary: Groups, sorts, and formats import statements.
Home-page: UNKNOWN
Author: Ted Kaemming, Disqus
Author-email: ted@disqus.com
License: UNKNOWN
Platform: UNKNOWN
